omnicart_pipeline/__init__.py
omnicart_pipeline/pipeline/__init__.py
omnicart_pipeline/pipeline/api_client.py
omnicart_pipeline/pipeline/cli.py
omnicart_pipeline/pipeline/config.py
omnicart_pipeline/pipeline/data_analyzer.py
omnicart_pipeline/pipeline/data_enricher.py
omnicart_pipeline/pipeline/pipeline.py
omnicart_pipeline/pipeline/sample.py
omnicart_pipeline/pipeline.cfg
omnicart_pipeline/README.md
omnicart_pipeline/requirements.txt
omnicart_pipeline/tests/__init__.py
omnicart_pipeline/tests/test_api_client.py
omnicart_pipeline/tests/test_config.py
omnicart_pipeline/tests/test_data_analyzer.py
omnicart_pipeline/tests/test_data_enricher.py
omnicart_pipeline_obaloluwaadeleke-0.1.1.dist-info/entry_points.txt
omnicart_pipeline_obaloluwaadeleke-0.1.1.dist-info/METADATA
omnicart_pipeline_obaloluwaadeleke-0.1.1.dist-info/WHEEL
omnicart_pipeline_obaloluwaadeleke-0.1.1.dist-info/RECORD
