Metadata-Version: 2.4
Name: omnicart-pipeline-ObaloluwaAdeleke
Version: 0.1.1
Summary: OmniCart data pipeline
Author: DeksTheAnalyst
Author-email: pdeks20@gmail.com
Requires-Python: >=3.10,<3.14
Classifier: Programming Language :: Python :: 3
Classifier: Programming Language :: Python :: 3.10
Classifier: Programming Language :: Python :: 3.11
Classifier: Programming Language :: Python :: 3.12
Classifier: Programming Language :: Python :: 3.13
Requires-Dist: pandas (>=2.0.0,<3.0.0)
Requires-Dist: requests (>=2.31.0,<3.0.0)
